clientwrapper/__init__.py
clientwrapper/basicmapping.py
clientwrapper/clientwrapper.py
clientwrapper/responsemapping.py
clientwrapper/utils.py
test_clientwrapper/__init__.py
test_clientwrapper/test_basicmapping.py
test_clientwrapper/test_clientwrapper.py
test_clientwrapper/test_resultmapping.py
clientwrapper-1.0.1.dist-info/LICENSE
clientwrapper-1.0.1.dist-info/METADATA
clientwrapper-1.0.1.dist-info/WHEEL
clientwrapper-1.0.1.dist-info/top_level.txt
clientwrapper-1.0.1.dist-info/RECORD
