Metadata-Version: 2.1
Name: clientwrapper
Version: 1.0.1
Summary: Python Util Package for inheriting Argparse behavior
Author-email: Joseph Gonzalez Diaz <jgonzalezdiaz@ebay.com>
Project-URL: Homepage, https://github.com/ebay/clientwrapper
Project-URL: Issues, https://github.com/ebay/clientwrapper/issues
Classifier: Programming Language :: Python :: 3
Classifier: License :: OSI Approved :: Apache Software License
Classifier: Operating System :: OS Independent
Requires-Python: >=3.8
License-File: LICENSE
